awslabs/__init__.py
awslabs/bedrock_kb_retrieval_mcp_server/__init__.py
awslabs/bedrock_kb_retrieval_mcp_server/models.py
awslabs/bedrock_kb_retrieval_mcp_server/server.py
awslabs/bedrock_kb_retrieval_mcp_server/knowledgebases/__init__.py
awslabs/bedrock_kb_retrieval_mcp_server/knowledgebases/clients.py
awslabs/bedrock_kb_retrieval_mcp_server/knowledgebases/discovery.py
awslabs/bedrock_kb_retrieval_mcp_server/knowledgebases/retrieval.py
mseep_awslabs_bedrock_kb_retrieval_mcp_server-1.0.2.dist-info/licenses/LICENSE
mseep_awslabs_bedrock_kb_retrieval_mcp_server-1.0.2.dist-info/licenses/NOTICE
tests/__init__.py
tests/conftest.py
tests/test_clients.py
tests/test_discovery.py
tests/test_env_config.py
tests/test_models.py
tests/test_retrieval.py
tests/test_server.py
mseep_awslabs_bedrock_kb_retrieval_mcp_server-1.0.2.dist-info/METADATA
mseep_awslabs_bedrock_kb_retrieval_mcp_server-1.0.2.dist-info/WHEEL
mseep_awslabs_bedrock_kb_retrieval_mcp_server-1.0.2.dist-info/top_level.txt
mseep_awslabs_bedrock_kb_retrieval_mcp_server-1.0.2.dist-info/RECORD
